politenessr/__init__.py
politenessr/convert_examples_to_features.py
politenessr/download_features.py
politenessr/politenessr.py
politenessr/predict.py
politenessr/regression_processor.py
politenessr-1.3.dist-info/METADATA
politenessr-1.3.dist-info/WHEEL
politenessr-1.3.dist-info/top_level.txt
politenessr-1.3.dist-info/RECORD
